fermisdk/__init__.py
fermisdk/_version.py
fermisdk/basesdk.py
fermisdk/brain.py
fermisdk/chat_and_sessions.py
fermisdk/data_connectors.py
fermisdk/httpclient.py
fermisdk/py.typed
fermisdk/sdk.py
fermisdk/sdkconfiguration.py
fermisdk/_hooks/__init__.py
fermisdk/_hooks/registration.py
fermisdk/_hooks/sdkhooks.py
fermisdk/_hooks/types.py
fermisdk/errors/__init__.py
fermisdk/errors/error.py
fermisdk/errors/fermisdkdefaulterror.py
fermisdk/errors/fermisdkerror.py
fermisdk/errors/no_response_error.py
fermisdk/errors/responsevalidationerror.py
fermisdk/models/__init__.py
fermisdk/models/chatcontent.py
fermisdk/models/chatrequest.py
fermisdk/models/chatresponse.py
fermisdk/models/chatsource.py
fermisdk/models/chatsources.py
fermisdk/models/connection.py
fermisdk/models/connectionlist.py
fermisdk/models/connectionmetadatarequest.py
fermisdk/models/connectionmetadataresponse.py
fermisdk/models/connectsessionrequest.py
fermisdk/models/connectsessionresponse.py
fermisdk/models/databasemetadatarequest.py
fermisdk/models/databasemetadataresponse.py
fermisdk/models/deleteconnectionop.py
fermisdk/models/documentuploadresponse.py
fermisdk/models/getconnectionmetadataop.py
fermisdk/models/getconnectionop.py
fermisdk/models/getsessioninfoop.py
fermisdk/models/listconnectionsop.py
fermisdk/models/listsessionsop.py
fermisdk/models/performvisualizationop.py
fermisdk/models/security.py
fermisdk/models/sessionactionrequest.py
fermisdk/models/sessionactionresponse.py
fermisdk/models/sessioninfo.py
fermisdk/models/sessionlistresponse.py
fermisdk/models/sessionsummary.py
fermisdk/models/syncenqueuerequest.py
fermisdk/models/syncenqueueresponse.py
fermisdk/models/testconnectionrequest.py
fermisdk/models/testconnectionresponse.py
fermisdk/models/uploaddocumentsop.py
fermisdk/models/visualizationrequest.py
fermisdk/models/visualizationresponsejson.py
fermisdk/types/__init__.py
fermisdk/types/basemodel.py
fermisdk/utils/__init__.py
fermisdk/utils/annotations.py
fermisdk/utils/datetimes.py
fermisdk-0.0.5.dist-info/METADATA
fermisdk-0.0.5.dist-info/WHEEL
fermisdk-0.0.5.dist-info/top_level.txt
fermisdk-0.0.5.dist-info/RECORD
